gothon.py
__pycache__/gothon.cpython-36.opt-2.pyc
gothon-0.5.0.dist-info/METADATA
gothon-0.5.0.dist-info/RECORD
gothon-0.5.0.dist-info/WHEEL
gothon-0.5.0.dist-info/top_level.txt
gothon-0.5.0.dist-info/zip-safe
