Metadata-Version: 2.1
Name: gothon
Version: 0.5.0
Summary: Gothon runs GO Code from Python, just import *.go files from Python.
Home-page: https://github.com/juancarlospaco/gothon#gothon
Author: Juan Carlos
Author-email: juancarlospaco@gmail.com
Maintainer: Juan Carlos
Maintainer-email: juancarlospaco@gmail.com
License: BSD
Download-URL: https://github.com/juancarlospaco/gothon#gothon
Project-URL: Docs, https://github.com/juancarlospaco/gothon/README.md
Project-URL: Bugs, https://github.com/juancarlospaco/gothon/issues
Project-URL: C.I., https://travis-ci.org/juancarlospaco/gothon
Project-URL: Chat, https://t.me/juancarlospaco
Keywords: minimalism,python3,go,golang,ipc,rpc,json,socket,import-hook,speed
Platform: Linux
Platform: Darwin
Classifier: Environment :: Console
Classifier: Environment :: No Input/Output (Daemon)
Classifier: Environment :: Other Environment
Classifier: Intended Audience :: Developers
Classifier: Intended Audience :: System Administrators
Classifier: Intended Audience :: Other Audience
Classifier: Natural Language :: English
Classifier: Operating System :: OS Independent
Classifier: Operating System :: POSIX :: Linux
Classifier: Operating System :: MacOS :: MacOS X
Classifier: Programming Language :: Python
Classifier: Programming Language :: Python :: 3
Classifier: Programming Language :: Python :: 3 :: Only
Classifier: Programming Language :: Python :: 3.6
Classifier: Programming Language :: Python :: Implementation :: CPython
Classifier: Topic :: Software Development
Classifier: Topic :: Software Development :: Libraries
Classifier: Topic :: Software Development :: Libraries :: Python Modules
Provides: gothon
Requires-Python: >=3.6
